api/game.proto
api/metadata/camera_settings.proto
api/metadata/game_metadata.proto
api/metadata/mutators.proto
api/metadata/player_loadout.proto
api/party.proto
api/player.proto
api/player_id.proto
api/stats/ball_stats.proto
api/stats/data_frame.proto
api/stats/dropshot.proto
api/stats/events.proto
api/stats/extra_mode_stats.proto
api/stats/game_stats.proto
api/stats/goal.proto
api/stats/kickoff.proto
api/stats/per_possession_stats.proto
api/stats/player_stats.proto
api/stats/rumble.proto
api/stats/stats.proto
api/stats/team_stats.proto
api/team.proto
carball/__init__.py
carball/_lib.cpython-312-darwin.so
carball/_lib.cpython-313-darwin.so
carball/analysis/PROTOBUF_VERSION
carball/analysis/__init__.py
carball/analysis/analysis_manager.py
carball/analysis/cleaner/__init__.py
carball/analysis/cleaner/cleaner.py
carball/analysis/cleaner/frame_cleaner.py
carball/analysis/constants/__init__.py
carball/analysis/constants/basic_math.py
carball/analysis/constants/dropshot.py
carball/analysis/constants/field_constants.py
carball/analysis/constants/playlist.py
carball/analysis/events/__init__.py
carball/analysis/events/boost_pad_detection/__init__.py
carball/analysis/events/boost_pad_detection/pickup_analysis.py
carball/analysis/events/bump_detection/__init__.py
carball/analysis/events/bump_detection/bump_analysis.py
carball/analysis/events/carry_detection.py
carball/analysis/events/dropshot/__init__.py
carball/analysis/events/dropshot/ball.py
carball/analysis/events/dropshot/damage.py
carball/analysis/events/event_creator.py
carball/analysis/events/fifty_fifty/__init__.py
carball/analysis/events/fifty_fifty/fifty_analysis.py
carball/analysis/events/hit_detection/__init__.py
carball/analysis/events/hit_detection/base_hit.py
carball/analysis/events/hit_detection/hit_analysis.py
carball/analysis/events/hit_detection/hitbox/__init__.py
carball/analysis/events/hit_detection/hitbox/car.py
carball/analysis/events/hit_detection/hitbox/hitbox.py
sprocket_rl_parser-1.2.16.dist-info/METADATA
sprocket_rl_parser-1.2.16.dist-info/WHEEL
sprocket_rl_parser-1.2.16.dist-info/entry_points.txt
sprocket_rl_parser-1.2.16.dist-info/licenses/LICENSE
sprocket_rl_parser-1.2.16.dist-info/licenses/NOTICE
sprocket_rl_parser-1.2.16.dist-info/RECORD
